vdfpy/__init__.py
vdfpy/clustering.py
vdfpy/fleks/__init__.py
vdfpy/fleks/fleks.py
vdfpy/generator/__init__.py
vdfpy/generator/generator.py
vdfpy/spedas/__init__.py
vdfpy/spedas/spedas.py
vdfpy/vdfpy.py
vdfpy/vlasiator/__init__.py
vdfpy/vlasiator/vlasiator.py
vdfpy-0.1.1.dist-info/LICENSE
vdfpy-0.1.1.dist-info/METADATA
vdfpy-0.1.1.dist-info/WHEEL
vdfpy-0.1.1.dist-info/RECORD
