Metadata-Version: 2.1
Name: vdfpy
Version: 0.1.1
Summary: Velocity distribution function classifier
Author: Hongyang Zhou
Author-email: hyzhou@umich.edu
Requires-Python: >=3.11,<4.0
Classifier: Programming Language :: Python :: 3
Classifier: Programming Language :: Python :: 3.11
Classifier: Programming Language :: Python :: 3.12
Classifier: Programming Language :: Python :: 3.13
Requires-Dist: flekspy (>=0.2.3,<0.3.0)
Requires-Dist: pandas (>=2.2.3,<3.0.0)
Requires-Dist: pyspedas (>=1.7.1,<2.0.0)
Requires-Dist: pyvlasiator (>=0.1.4,<0.2.0)
Requires-Dist: scikit-learn (>=1.5.2,<2.0.0)
Requires-Dist: scipy (>=1.14.1,<2.0.0)
Requires-Dist: umap-learn (>=0.5.7,<0.6.0)
